{
  "name": "Data Scientist Roadmap",
  "url": "https://www.scaler.com/blog/how-to-become-a-data-scientist/",
  "description": "|_Data science is an excellent career choice in today’s data-driven world where approx 328.77 million terabytes of data are generated daily. And this number is only increasing day by day, which in turn increases the demand for skilled data scientists who can utilize this data to drive business growt",
  "section": "What is Data Science?",
  "topic": "data_science",
  "category": "cat1_science",
  "source": "github_awesome"
}